Lab1/Example/l0q1.v
module l0q1(f,a,b,c);
	input a,b,c;
	output f;
	and (m,a,b);
	not (k,b);
	and (n,k,c);
	or (f,m,n);
endmodule

Lab1/Example/l0q1_tb.v
`timescale 1ns/1ns
`include "l0q1.v"

module l0q1_tb();
reg a,b,c;
wire f;

l0q1 ex1(f,a,b,c);
initial
begin

	$dumpfile("l0q1_tb.vcd");
	$dumpvars(0,l0q1_tb);
	
	a=1'b0;b=1'b0;c=1'b0;
	#20;
	
	a=1'b0;b=1'b0;c=1'b1;
	#20;
	
	a=1'b0;b=1'b1;c=1'b0;
	#20;
	
	a=1'b0;b=1'b1;c=1'b1;
	#20;
	
	a=1'b1;b=1'b0;c=1'b0;
	#20;
	
	a=1'b1;b=1'b0;c=1'b1;
	#20;
	
	a=1'b1; b=1'b1; c=1'b0;
	#20;
	
	a=1'b1;b=1'b1;c=1'b1;
	#20;
	
	$display("Test Complete");

end
endmodule

Lab1/Example/l0q1_tb.vcd
$date
	Mon Jul 27 10:05:34 2026
$end
$version
	Icarus Verilog
$end
$timescale
	1ns
$end
$scope module l0q1_tb $end
$var wire 1 ! f $end
$var reg 1 " a $end
$var reg 1 # b $end
$var reg 1 $ c $end
$scope module ex1 $end
$var wire 1 " a $end
$var wire 1 # b $end
$var wire 1 $ c $end
$var wire 1 ! f $end
$var wire 1 % k $end
$var wire 1 & m $end
$var wire 1 ' n $end
$upscope $end
$upscope $end
$enddefinitions $end
#0
$dumpvars
0'
0&
1%
0$
0#
0"
0!
$end
#20
1!
1'
1$
#40
0!
0'
0%
0$
1#
#60
1$
#80
1%
0$
0#
1"
#100
1!
1'
1$
#120
0'
1&
0%
0$
1#
#140
1$
