Lab4/q1/q1b.v
module q1b(sum,Cout,a,b,Cin);
	input a,b,Cin;
	output sum,Cout;
	assign sum=a^b^Cin;
	assign Cout=(a&b)|(b&Cin)|(Cin&a);
endmodule

Lab4/q1/q1b_tb.v
`timescale 1ns/1ns
`include "q1b.v"

module q1b_tb();
reg a,b,Cin;
wire sum,Cout;

q1b ex1(sum,Cout,a,b,Cin);
initial
begin

	$dumpfile("q1b_tb.vcd");
	$dumpvars(0,q1b_tb);
	
	a=1'b0;b=1'b0;Cin=1'b0;
	#20;
	
	a=1'b0;b=1'b0;Cin=1'b1;
	#20;
	
	a=1'b0;b=1'b1;Cin=1'b0;
	#20;
	
	a=1'b0;b=1'b1;Cin=1'b1;
	#20;
	
	a=1'b1;b=1'b0;Cin=1'b0;
	#20;
	
	a=1'b1;b=1'b0;Cin=1'b1;
	#20;
	
	a=1'b1;b=1'b1;Cin=1'b0;
	#20;
	
	a=1'b1;b=1'b1;Cin=1'b1;
	#20;
	
	$display("Test Complete");

end
endmodule

Lab4/q1/q1b_tb.vcd
$date
	Mon Aug 17 08:18:57 2026
$end
$version
	Icarus Verilog
$end
$timescale
	1ns
$end
$scope module q1b_tb $end
$var wire 1 ! sum $end
$var wire 1 " Cout $end
$var reg 1 # Cin $end
$var reg 1 $ a $end
$var reg 1 % b $end
$scope module ex1 $end
$var wire 1 # Cin $end
$var wire 1 " Cout $end
$var wire 1 $ a $end
$var wire 1 % b $end
$var wire 1 ! sum $end
$upscope $end
$upscope $end
$enddefinitions $end
#0
$dumpvars
0%
0$
0#
0"
0!
$end
#20
1!
1#
#40
0#
1%
#60
1"
0!
1#
#80
0"
1!
0#
0%
1$
#100
1"
0!
1#
#120
0#
1%
#140
1!
1#
