Lab3/q4/q4.v
module q4(f,a,b,c,d);
	input a,b,c,d;
	output f;
	nand (x,a,a);
	nand (y,b,b);
	nand (z,d,d);
	nand (p,x,y);
	nand (q,c,d);
	nand (r,z,y);
	nand (f,p,q,r);
endmodule

Lab2/q4/q4_tb.v
`timescale 1ns/1ns
`include "q4.v"

module q4_tb();
reg a,b,c,d;
wire f;

q4 ex1(f,a,b,c,d);
initial
begin

	$dumpfile("q4_tb.vcd");
	$dumpvars(0,q4_tb);
	
	a=1'b0;b=1'b0;c=1'b0;d=1'b0;
	#20;
	
	a=1'b0;b=1'b0;c=1'b0;d=1'b1;
	#20;
	
	a=1'b0;b=1'b0;c=1'b1;d=1'b0;
	#20;
	
	a=1'b0;b=1'b0;c=1'b1;d=1'b1;
	#20;
	
	a=1'b0;b=1'b1;c=1'b0;d=1'b0;
	#20;
	
	a=1'b0;b=1'b1;c=1'b0;d=1'b1;
	#20;
	
	a=1'b0;b=1'b1;c=1'b1;d=1'b0;
	#20;
	
	a=1'b0;b=1'b1;c=1'b1;d=1'b1;
	#20;
	
	a=1'b1;b=1'b0;c=1'b0;d=1'b0;
	#20;
	
	a=1'b1;b=1'b0;c=1'b0;d=1'b1;
	#20;
	
	a=1'b1;b=1'b0;c=1'b1;d=1'b0;
	#20;
	
	a=1'b1;b=1'b0;c=1'b1;d=1'b1;
	#20;
	
	a=1'b1;b=1'b1;c=1'b0;d=1'b0;
	#20;
	
	a=1'b1;b=1'b1;c=1'b0;d=1'b1;
	#20;
	
	a=1'b1;b=1'b1;c=1'b1;d=1'b0;
	#20;
	
	a=1'b1;b=1'b1;c=1'b1;d=1'b1;
	#20;
	
	$display("Test Complete");

end
endmodule

Lab3/q4/q4_tb.vcd
$date
	Mon Aug 10 10:57:05 2026
$end
$version
	Icarus Verilog
$end
$timescale
	1ns
$end
$scope module q4_tb $end
$var wire 1 ! f $end
$var reg 1 " a $end
$var reg 1 # b $end
$var reg 1 $ c $end
$var reg 1 % d $end
$scope module ex1 $end
$var wire 1 " a $end
$var wire 1 # b $end
$var wire 1 $ c $end
$var wire 1 % d $end
$var wire 1 ! f $end
$var wire 1 & p $end
$var wire 1 ' q $end
$var wire 1 ( r $end
$var wire 1 ) x $end
$var wire 1 * y $end
$var wire 1 + z $end
$upscope $end
$upscope $end
$enddefinitions $end
#0
$dumpvars
1+
1*
1)
0(
1'
0&
0%
0$
0#
0"
1!
$end
#20
1(
0+
1%
#40
0(
1+
0%
1$
#60
1(
0+
0'
1%
#80
0!
1&
1+
1'
0*
0%
0$
1#
#100
0+
1%
#120
1+
0%
1$
#140
1!
0+
0'
1%
#160
0(
1+
1'
1*
0)
0%
0$
0#
1"
#180
0!
1(
0+
1%
#200
1!
0(
1+
0%
1$
#220
1(
0+
0'
1%
#240
0!
1+
1'
0*
0%
0$
1#
#260
0+
1%
#280
1+
0%
1$
#300
1!
0+
0'
1%
