Lab3/q3/q3.v
module q3(f,a,b,c,d);
	input a,b,c,d;
	output f;
	nor (x,a,a);
	nor (y,c,c);
	nor (p,b,d);
	nor (q,a,d);
	nor (r,y,x);
	nor (f,p,q,r);
endmodule

Lab2/q3/q3_tb.v
`timescale 1ns/1ns
`include "q3.v"

module q3_tb();
reg a,b,c,d;
wire f;

q3 ex1(f,a,b,c,d);
initial
begin

	$dumpfile("q3_tb.vcd");
	$dumpvars(0,q3_tb);
	
	a=1'b0;b=1'b0;c=1'b0;d=1'b0;
	#20;
	
	a=1'b0;b=1'b0;c=1'b0;d=1'b1;
	#20;
	
	a=1'b0;b=1'b0;c=1'b1;d=1'b0;
	#20;
	
	a=1'b0;b=1'b0;c=1'b1;d=1'b1;
	#20;
	
	a=1'b0;b=1'b1;c=1'b0;d=1'b0;
	#20;
	
	a=1'b0;b=1'b1;c=1'b0;d=1'b1;
	#20;
	
	a=1'b0;b=1'b1;c=1'b1;d=1'b0;
	#20;
	
	a=1'b0;b=1'b1;c=1'b1;d=1'b1;
	#20;
	
	a=1'b1;b=1'b0;c=1'b0;d=1'b0;
	#20;
	
	a=1'b1;b=1'b0;c=1'b0;d=1'b1;
	#20;
	
	a=1'b1;b=1'b0;c=1'b1;d=1'b0;
	#20;
	
	a=1'b1;b=1'b0;c=1'b1;d=1'b1;
	#20;
	
	a=1'b1;b=1'b1;c=1'b0;d=1'b0;
	#20;
	
	a=1'b1;b=1'b1;c=1'b0;d=1'b1;
	#20;
	
	a=1'b1;b=1'b1;c=1'b1;d=1'b0;
	#20;
	
	a=1'b1;b=1'b1;c=1'b1;d=1'b1;
	#20;
	
	$display("Test Complete");

end
endmodule

Lab3/q3/q3_tb.vcd
$date
	Mon Aug 10 10:56:18 2026
$end
$version
	Icarus Verilog
$end
$timescale
	1ns
$end
$scope module q3_tb $end
$var wire 1 ! f $end
$var reg 1 " a $end
$var reg 1 # b $end
$var reg 1 $ c $end
$var reg 1 % d $end
$scope module ex1 $end
$var wire 1 " a $end
$var wire 1 # b $end
$var wire 1 $ c $end
$var wire 1 % d $end
$var wire 1 ! f $end
$var wire 1 & p $end
$var wire 1 ' q $end
$var wire 1 ( r $end
$var wire 1 ) x $end
$var wire 1 * y $end
$upscope $end
$upscope $end
$enddefinitions $end
#0
$dumpvars
1*
1)
0(
1'
1&
0%
0$
0#
0"
0!
$end
#20
1!
0&
0'
1%
#40
0!
1&
1'
0*
0%
1$
#60
1!
0&
0'
1%
#80
0!
1'
1*
0%
0$
1#
#100
1!
0'
1%
#120
0!
1'
0*
0%
1$
#140
1!
0'
1%
#160
0!
1*
1&
0)
0%
0$
0#
1"
#180
1!
0&
1%
#200
0!
1(
1&
0*
0%
1$
#220
0&
1%
#240
1!
0(
1*
0%
0$
1#
#260
1%
#280
0!
1(
0*
0%
1$
#300
1%
